forsee/__init__.py
forsee/args_handler.py
forsee/forsee.py
forsee/forsee_functions.py
forsee-0.1.1.dist-info/METADATA
forsee-0.1.1.dist-info/WHEEL
forsee-0.1.1.dist-info/entry_points.txt
forsee-0.1.1.dist-info/top_level.txt
forsee-0.1.1.dist-info/RECORD
