Metadata-Version: 2.1
Name: forsee
Version: 0.1.1
Summary: Exports a compile_commands.json from a Crosscore Project
Author: Nikos Tzekas
Author-email: nt@itec-audio.com
